{
  "project_info": {
    "project_number": "997443237631",
    "firebase_url": "https://reactnativetodo-2f2df.firebaseio.com",
    "project_id": "reactnativetodo-2f2df",
    "storage_bucket": "reactnativetodo-2f2df.appspot.com"
  },
  "client": [
    {
      "client_info": {
        "mobilesdk_app_id": "1:997443237631:android:c2f1f7a2f5d1a07226beca",
        "android_client_info": {
          "package_name": "com.januswel.praiser"
        }
      },
      "oauth_client": [
        {
          "client_id": "997443237631-nkglotddp0mu42v7m3n2l953aeamobv0.apps.googleusercontent.com",
          "client_type": 1,
          "android_info": {
            "package_name": "com.januswel.praiser",
            "certificate_hash": "f7edfd894cc152cac6285d4283ab0e42c0513fea"
          }
        },
        {
          "client_id": "997443237631-ekg4lp650oghl1utuclbhtkf2btf1mrc.apps.googleusercontent.com",
          "client_type": 3
        }
      ],
      "api_key": [
        {
          "current_key": "AIzaSyBVZCqwIBj-pEixKglGFWZihyewa-IptJA"
        }
      ],
      "services": {
        "appinvite_service": {
          "other_platform_oauth_client": [
            {
              "client_id": "997443237631-ekg4lp650oghl1utuclbhtkf2btf1mrc.apps.googleusercontent.com",
              "client_type": 3
            },
            {
              "client_id": "997443237631-la6am5c0d84d2qk77s0t7is8kc7t3ve9.apps.googleusercontent.com",
              "client_type": 2,
              "ios_info": {
                "bundle_id": "com.januswel.praiser"
              }
            }
          ]
        }
      }
    }
  ],
  "configuration_version": "1"
}